negotiator_host/__init__.py
negotiator_host/cli.py
negotiator_host-0.12.2.dist-info/LICENSE.txt
negotiator_host-0.12.2.dist-info/METADATA
negotiator_host-0.12.2.dist-info/WHEEL
negotiator_host-0.12.2.dist-info/entry_points.txt
negotiator_host-0.12.2.dist-info/top_level.txt
negotiator_host-0.12.2.dist-info/RECORD
