Metadata-Version: 2.1
Name: negotiator-host
Version: 0.12.2
Summary: Scriptable KVM/QEMU guest agent (host side of things)
Home-page: https://negotiator.readthedocs.org
Author: Peter Odding
Author-email: peter@peterodding.com
License: MIT
Platform: UNKNOWN
Classifier: Development Status :: 4 - Beta
Classifier: Environment :: Console
Classifier: Intended Audience :: Developers
Classifier: Intended Audience :: Information Technology
Classifier: Intended Audience :: System Administrators
Classifier: License :: OSI Approved :: MIT License
Classifier: Operating System :: POSIX
Classifier: Operating System :: POSIX :: Linux
Classifier: Operating System :: Unix
Classifier: Programming Language :: Python
Classifier: Programming Language :: Python :: 2
Classifier: Programming Language :: Python :: 2.6
Classifier: Programming Language :: Python :: 2.7
Classifier: Programming Language :: Python :: 3
Classifier: Programming Language :: Python :: 3.4
Classifier: Topic :: Communications
Classifier: Topic :: Software Development
Classifier: Topic :: System
Classifier: Topic :: System :: Installation/Setup
Classifier: Topic :: System :: Operating System
Classifier: Topic :: System :: Operating System Kernels :: Linux
Classifier: Topic :: System :: Systems Administration
Requires-Dist: coloredlogs (>=5.0)
Requires-Dist: negotiator-common (>=0.12.2)
